bloompy/__init__.py
bloompy-0.1.1.dist-info/LICENSE
bloompy-0.1.1.dist-info/METADATA
bloompy-0.1.1.dist-info/WHEEL
bloompy-0.1.1.dist-info/top_level.txt
bloompy-0.1.1.dist-info/RECORD
