Metadata-Version: 2.1
Name: bloompy
Version: 0.1.1
Summary: Implementation of Bloom Filter.
Home-page: https://github.com/01ly/bloompy
Author: linkin
Author-email: yooleak@outlook.com
License: UNKNOWN
Platform: UNKNOWN
Classifier: Programming Language :: Python :: 3
Classifier: License :: OSI Approved :: BSD License
Classifier: Operating System :: OS Independent
Requires-Dist: bitarray (>=0.8.3)
Requires-Dist: mmh3 (>=2.5.1)
